scs/__init__.py
scs/captcha.py
src/__init__.py
src/captcha.py
selenium_captcha_solver-0.0.3.dist-info/LICENSE
selenium_captcha_solver-0.0.3.dist-info/METADATA
selenium_captcha_solver-0.0.3.dist-info/WHEEL
selenium_captcha_solver-0.0.3.dist-info/top_level.txt
selenium_captcha_solver-0.0.3.dist-info/RECORD
